Obscheme-0.3.0.dist-info/DESCRIPTION.rst
Obscheme-0.3.0.dist-info/METADATA
Obscheme-0.3.0.dist-info/RECORD
Obscheme-0.3.0.dist-info/WHEEL
Obscheme-0.3.0.dist-info/metadata.json
Obscheme-0.3.0.dist-info/top_level.txt
obscheme/__init__.py
obscheme/exceptions.py
obscheme/field.py
obscheme/schema.py
obscheme/schemameta.py
obscheme/util.py
obscheme/fields/__init__.py
obscheme/fields/int32.py
obscheme/fields/int64.py
obscheme/fields/integer.py
obscheme/fields/list.py
obscheme/fields/nillable.py
obscheme/fields/schema_object.py
obscheme/fields/string.py
obscheme/tests/__init__.py
obscheme/tests/test_field_integer.py
obscheme/tests/test_field_list.py
obscheme/tests/test_field_string.py
obscheme/tests/test_invariant.py
obscheme/tests/test_schema.py
obscheme/tests/test_schema_object_factor.py
obscheme/tests/test_schema_slots.py
obscheme/tests/test_undefined_field.py
