Metadata-Version: 2.0
Name: Obscheme
Version: 0.3.0
Summary: Define and enforce schema on objects
Home-page: https://github.com/twiebe/Obscheme
Author: Thomas Wiebe
Author-email: code@heimblick.net
License: BSD
Platform: any
Classifier: Intended Audience :: Developers
Classifier: License :: OSI Approved :: BSD License
Classifier: Operating System :: OS Independent
Classifier: Programming Language :: Python
Classifier: Topic :: Software Development :: Libraries :: Python Modules
